{
	"format_version": "1.8.0",
	"animations": {
		"call": {
			"loop": "hold_on_last_frame",
			"animation_length": 0.7311,
			"bones": {
				"center": {
					"rotation": [0, 0, 0],
					"position": {
						"0.0": [0, 0, 43],
						"0.7308": [0, 0, 0]
					}
				},
				"right": {
					"rotation": [22.5, 0, 30],
					"position": {
						"0.0": [0, 0, 43],
						"0.7308": [0, 0, 0]
					}
				},
				"left": {
					"rotation": [22.5, 0, -30],
					"position": {
						"0.0": [0, 0, 43],
						"0.7308": [0, 0, 0]
					}
				},
				"right_2": {
					"rotation": [22.5, 0, 10],
					"position": {
						"0.0": [0, 0, 43],
						"0.7308": [0, 0, 0]
					}
				},
				"left_2": {
					"rotation": [22.5, 0, -10],
					"position": {
						"0.0": [0, 0, 43],
						"0.7308": [0, 0, 0]
					}
				}
			}
		}
	}
}