{
  "type": "palladium:compound",
  "layers": [
    {
      "type": "geckolib:default",
      "model": "satsu_iron_man_addon:geo/glases.geo.json",
      "texture": "satsu_iron_man_addon:textures/models/glasses.png",
      "conditions": [
        {
          "type": "palladium:not",
          "conditions": [
            {
              "type": "palladium:objective_score",
              "objective": "satsu.iron.man.armor.remote",
              "min_score": 1,
              "max_score": 1
            }
          ]
        },
        {
          "type": "palladium:not",
          "conditions": [
            {
              "type": "palladium:objective_score",
              "objective": "satsu.iron.man.armor.actived",
              "min_score": 1,
              "max_score": 1
            }
          ]
        }
      ]
    }
  ]
}
