{
  "name": { "translate": "ability.title.satsu.ia" },
  "ability_bar_texture": "#satsu_iron_man_addon:armor_hud/ability_bar",
  "background": "satsu_iron_man_addon:textures/gui/block/background.png",
  "icon": "satsu_iron_man_addon:textures/item/nanoparticle_secondary_color_change.png",
  "gui_display_type": "tree",
  "abilities": {
    "skill_tree": {
      "type": "palladium:dummy",
      "icon": "satsu_iron_man_addon:textures/item/nanoparticle_secondary_color_change.png",
      "title": {
        "translate": "ability.title.satsu.nanoparticle_secondary_color_change"
      },
      "description": {
        "translate": "description.satsu.nanoparticle_secondary_color_change"
      },
      "hidden": false,
      "hidden_in_bar": true,
      "list_index": 0,
      "gui_position": [0, 0],
      "conditions": {
        "enabling": [],
        "unlocking": []
      }
    },
    "choose.ia": {
      "type": "palladium:ability_wheel",
      "icon": "satsu_iron_man_addon:textures/item/nanoparticle_secondary_color_change.png",
      "title": { "translate": "ability.title.satsu.ia.choose" },
      "description": { "translate": "description.satsu.ia.choose" },
      "hidden": false,
      "hidden_in_bar": false,
      "list_index": 0,
      "gui_position": [0, 0.5],
      "abilities": [
        "color.1",
        "color.2",
        "color.3",
        "color.4",
        "color.5",
        "color.6"
      ],
      "conditions": {
        "enabling": [
          {
            "type": "palladium:held",
            "cooldown": 0,
            "key_type": "key_bind",
            "needs_empty_hand": false,
            "allow_scrolling_when_crouching": true
          }
        ],
        "unlocking": [
          {
            "type": "palladium:ability_unlocked",
            "power": "satsu_iron_man_addon:items/nanoparticle_secondary_color_change",
            "ability": "skill_tree"
          }
        ]
      }
    },
    "color.1": {
      "type": "palladium:command",
      "icon": "satsu_iron_man_addon:textures/gui/model_prime/change_color/secondary/color_0.png",
      "title": { "translate": "" },
      "description": { "translate": "description.satsu.ia.choose" },
      "hidden": false,
      "hidden_in_bar": false,
      "list_index": 0,
      "gui_position": [0, 0.5],
      "first_tick_commands": [
        "scoreboard players set @s satsu.iron.man.addon.model.prime.color.plate.choose 0"
      ],
      "commands": [""],
      "last_tick_commands": [],
      "conditions": {
        "enabling": [
          {
            "type": "palladium:ability_wheel",
            "cooldown": 0
          }
        ],
        "unlocking": [
          {
            "type": "palladium:ability_unlocked",
            "power": "satsu_iron_man_addon:items/nanoparticle_secondary_color_change",
            "ability": "skill_tree"
          }
        ]
      }
    },
    "color.2": {
      "type": "palladium:command",
      "icon": "satsu_iron_man_addon:textures/gui/model_prime/change_color/secondary/color_1.png",
      "title": { "translate": "" },
      "description": { "translate": "description.satsu.ia.choose" },
      "hidden": false,
      "hidden_in_bar": false,
      "list_index": 0,
      "gui_position": [0, 0.5],
      "first_tick_commands": [
        "scoreboard players set @s satsu.iron.man.addon.model.prime.color.plate.choose 1"
      ],
      "commands": [""],
      "last_tick_commands": [],
      "conditions": {
        "enabling": [
          {
            "type": "palladium:ability_wheel",
            "cooldown": 0
          }
        ],
        "unlocking": [
          {
            "type": "palladium:ability_unlocked",
            "power": "satsu_iron_man_addon:items/nanoparticle_secondary_color_change",
            "ability": "skill_tree"
          }
        ]
      }
    },
    "color.3": {
      "type": "palladium:command",
      "icon": "satsu_iron_man_addon:textures/gui/model_prime/change_color/secondary/color_2.png",
      "title": { "translate": "" },
      "description": { "translate": "description.satsu.ia.choose" },
      "hidden": false,
      "hidden_in_bar": false,
      "list_index": 0,
      "gui_position": [0, 0.5],
      "first_tick_commands": [
        "scoreboard players set @s satsu.iron.man.addon.model.prime.color.plate.choose 2"
      ],
      "commands": [""],
      "last_tick_commands": [],
      "conditions": {
        "enabling": [
          {
            "type": "palladium:ability_wheel",
            "cooldown": 0
          }
        ],
        "unlocking": [
          {
            "type": "palladium:ability_unlocked",
            "power": "satsu_iron_man_addon:items/nanoparticle_secondary_color_change",
            "ability": "skill_tree"
          }
        ]
      }
    },
    "color.4": {
      "type": "palladium:command",
      "icon": "satsu_iron_man_addon:textures/gui/model_prime/change_color/secondary/color_3.png",
      "title": { "translate": "" },
      "description": { "translate": "description.satsu.ia.choose" },
      "hidden": false,
      "hidden_in_bar": false,
      "list_index": 0,
      "gui_position": [0, 0.5],
      "first_tick_commands": [
        "scoreboard players set @s satsu.iron.man.addon.model.prime.color.plate.choose 3"
      ],
      "commands": [""],
      "last_tick_commands": [],
      "conditions": {
        "enabling": [
          {
            "type": "palladium:ability_wheel",
            "cooldown": 0
          }
        ],
        "unlocking": [
          {
            "type": "palladium:ability_unlocked",
            "power": "satsu_iron_man_addon:items/nanoparticle_secondary_color_change",
            "ability": "skill_tree"
          }
        ]
      }
    },
    "color.5": {
      "type": "palladium:command",
      "icon": "satsu_iron_man_addon:textures/gui/model_prime/change_color/secondary/color_4.png",
      "title": { "translate": "" },
      "description": { "translate": "description.satsu.ia.choose" },
      "hidden": false,
      "hidden_in_bar": false,
      "list_index": 0,
      "gui_position": [0, 0.5],
      "first_tick_commands": [
        "scoreboard players set @s satsu.iron.man.addon.model.prime.color.plate.choose 4"
      ],
      "commands": [""],
      "last_tick_commands": [],
      "conditions": {
        "enabling": [
          {
            "type": "palladium:ability_wheel",
            "cooldown": 0
          }
        ],
        "unlocking": [
          {
            "type": "palladium:ability_unlocked",
            "power": "satsu_iron_man_addon:items/nanoparticle_secondary_color_change",
            "ability": "skill_tree"
          }
        ]
      }
    },
    "color.6": {
      "type": "palladium:command",
      "icon": "satsu_iron_man_addon:textures/gui/model_prime/change_color/secondary/color_5.png",
      "title": { "translate": "" },
      "description": { "translate": "description.satsu.ia.choose" },
      "hidden": false,
      "hidden_in_bar": false,
      "list_index": 0,
      "gui_position": [0, 0.5],
      "first_tick_commands": [
        "scoreboard players set @s satsu.iron.man.addon.model.prime.color.plate.choose 5"
      ],
      "commands": [""],
      "last_tick_commands": [],
      "conditions": {
        "enabling": [
          {
            "type": "palladium:ability_wheel",
            "cooldown": 0
          }
        ],
        "unlocking": [
          {
            "type": "palladium:ability_unlocked",
            "power": "satsu_iron_man_addon:items/nanoparticle_secondary_color_change",
            "ability": "skill_tree"
          }
        ]
      }
    },
    "action": {
      "type": "palladium:command",
      "icon": "satsu_iron_man_addon:textures/gui/armors/placeholder.png",
      "title": { "translate": "ability.title.satsu.ia.name.0" },
      "description": { "translate": "description.satsu.ia.color" },
      "hidden": false,
      "hidden_in_bar": false,
      "list_index": 1,
      "gui_position": [0, 1],
      "commands": [""],
      "last_tick_commands": [
        "scoreboard players operation @s satsu.iron.man.addon.model.prime.color.plate = @s satsu.iron.man.addon.model.prime.color.plate.choose"
      ],
      "conditions": {
        "enabling": [
          {
            "type": "palladium:activation",
            "ticks": 20,
            "cooldown": 0,
            "key_type": "right_click",
            "needs_empty_hand": false
          }
        ],
        "unlocking": [
          {
            "type": "palladium:ability_unlocked",
            "power": "satsu_iron_man_addon:items/nanoparticle_secondary_color_change",
            "ability": "skill_tree"
          }
        ]
      }
    },
    "remove": {
      "type": "palladium:command",
      "hidden": true,
      "hidden_in_bar": true,
      "commands": [""],
      "last_tick_commands": [
        "scoreboard players reset @s satsu.iron.man.addon.model.prime.color.plate.choose"
      ],
      "conditions": {
        "enabling": [],
        "unlocking": []
      }
    }
  }
}
