{
  "name": { "translate": "ability.title.satsu.mark.4" },
  "allow_bar_shrinking": true,
  "ability_bar_texture": "#satsu_iron_man_addon:armor_hud/ability_bar",
  "background": "satsu_iron_man_addon:textures/block/crafting_table_top.png",
  "icon": "satsu_iron_man_addon:textures/gui/armors/new_icon/mark_head_icon_4.png",
  "abilities": {
    "armor": {
      "type": "palladium:dummy",
      "hidden": true,
      "hidden_in_bar": true,
      "conditions": {
        "enabling": [],
        "unlocking": [
          {
            "type": "palladium:has_power",
            "power": "satsu_iron_man_addon:armor_principal/iron_man_armor"
          },
          {
            "type": "satsu_iron_man_addon:dampened_by",
            "effect": "satsu_iron_man_addon:emp"
          },
          {
            "type": "satsu_iron_man_addon:disable_if_have_power_or_namespace",
            "powers": [
              "satsu_iron_man_addon:extremis/main",
              "satsu_iron_man_addon:ia_stuff/block_sentinel_functions/main"
            ],
            "namespaces": ["fsang", "fsang_hero", "gabeupsp"],
            "ignore_powers": ["fsang:space_power", "fsang_hero:dampened"]
          },
          {
            "type": "palladium:not",
            "conditions": [
              {
                "type": "palladium:or",
                "conditions": [
                  {
                    "type": "palladium:objective_score",
                    "objective": "satsu.iron.man.closed.armors",
                    "min_score": 1,
                    "max_score": 1
                  },
                  {
                    "type": "palladium:has_tag",
                    "tag": "alien"
                  },
                  {
                    "type": "palladium:has_tag",
                    "tag": "dampened"
                  }
                ]
              }
            ]
          }
        ]
      }
    },
    "dummy": {
      "type": "palladium:dummy",
      "icon": "satsu_iron_man_addon:textures/gui/armors/gantry.png",
      "title": { "translate": "ability.title.satsu.gantry" },
      "hidden": true,
      "hidden_in_bar": false,
      "list_index": 0,
      "conditions": {
        "enabling": [
          {
            "type": "palladium:toggle",
            "cooldown": 0,
            "key_type": "key_bind",
            "needs_empty_hand": false,
            "allow_scrolling_when_crouching": true
          }
        ],
        "unlocking": [
          {
            "type": "palladium:has_power",
            "power": "satsu_iron_man_addon:armor_principal/iron_man_armor"
          },
          {
            "type": "palladium:command_result",
            "command": "execute as @s if block ~ ~-1 ~ satsu_iron_man_addon:gantry_station"
          }
        ]
      }
    },
    "no-jump": {
      "type": "palladium:attribute_modifier",
      "hidden": true,
      "hidden_in_bar": true,
      "attribute": "palladium:jump_power",
      "amount": -1000000,
      "operation": 0,
      "uuid": "082a7fdc-3a09-4dc8-8c6b-d99b65670945",
      "conditions": {
        "enabling": [
          {
            "type": "palladium:ability_enabled",
            "ability": "dummy"
          }
        ],
        "unlocking": []
      }
    },
    "no-fly": {
      "type": "palladium:attribute_modifier",
      "hidden": true,
      "hidden_in_bar": true,
      "attribute": "palladium:flight_speed",
      "amount": -1000000,
      "operation": 0,
      "uuid": "4ba03a86-7ff5-48bb-8dd9-833c008e85c2",
      "conditions": {
        "enabling": [
          {
            "type": "palladium:ability_enabled",
            "ability": "dummy"
          }
        ],
        "unlocking": []
      }
    },
    "paralized.command": {
      "type": "palladium:command",
      "hidden": true,
      "hidden_in_bar": true,
      "first_tick_commands": [
        "effect give @s minecraft:slowness infinite 255 true"
      ],
      "commands": [""],
      "last_tick_commands": ["effect clear @s minecraft:slowness"],
      "conditions": {
        "enabling": [
          {
            "type": "palladium:ability_enabled",
            "ability": "dummy"
          }
        ],
        "unlocking": []
      }
    },
    "render_layer": {
      "type": "palladium:render_layer",
      "hidden": true,
      "hidden_in_bar": false,
      "render_layer": "satsu_iron_man_addon:gantry/main",
      "conditions": {
        "enabling": [
          {
            "type": "palladium:ability_enabled",
            "ability": "dummy"
          }
        ],
        "unlocking": []
      }
    },
    "render_layer_animation": {
      "type": "geckolib:render_layer_animation",
      "hidden": true,
      "hidden_in_bar": true,
      "render_layer": "satsu_iron_man_addon:gantry/main",
      "controller": "looping_controller",
      "animation_trigger": "animation",
      "conditions": {
        "enabling": [
          {
            "type": "palladium:or",
            "conditions": [
              {
                "type": "palladium:and",
                "conditions": [
                  {
                    "type": "palladium:ability_integer_property",
                    "ability": "armor_activate.animation_timer.every",
                    "property": "value",
                    "min": 1,
                    "max": 1
                  },
                  {
                    "type": "palladium:objective_score",
                    "objective": "satsu.iron.man.animation.armor",
                    "min_score": 1
                  }
                ]
              },
              {
                "type": "palladium:and",
                "conditions": [
                  {
                    "type": "palladium:ability_integer_property",
                    "ability": "armor_activate.animation_timer.every",
                    "property": "value",
                    "min": 19,
                    "max": 19
                  },
                  {
                    "type": "palladium:objective_score",
                    "objective": "satsu.iron.man.animation.armor",
                    "min_score": 0,
                    "max_score": 0
                  }
                ]
              }
            ]
          }
        ]
      }
    },
    "render_layer_animation.stand": {
      "type": "geckolib:render_layer_animation",
      "hidden": true,
      "hidden_in_bar": true,
      "render_layer": "satsu_iron_man_addon:gantry/main",
      "controller": "looping_controller",
      "animation_trigger": "stand",
      "conditions": {
        "enabling": [
          {
            "type": "palladium:or",
            "conditions": [
              {
                "type": "palladium:ability_integer_property",
                "power": "satsu_iron_man_addon:iron_man/marks/mark_3/main",
                "ability": "no_nanoarmor_anim",
                "property": "value",
                "min": 18,
                "max": 18
              },
              {
                "type": "palladium:ability_integer_property",
                "power": "satsu_iron_man_addon:iron_man/marks/mark_3/main",
                "ability": "no_nanoarmor_anim",
                "property": "value",
                "min": 1,
                "max": 1
              }
            ]
          }
        ]
      }
    },
    "armor_activate.animation_timer.every": {
      "type": "palladium:animation_timer",
      "hidden": true,
      "hidden_in_bar": true,
      "start_value": 0,
      "max_value": 20,
      "conditions": {
        "enabling": [
          {
            "type": "palladium:objective_score",
            "objective": "satsu.iron.man.animation.armor",
            "min_score": 1,
            "max_score": 1
          }
        ],
        "unlocking": [
          {
            "type": "palladium:or",
            "conditions": [
              {
                "type": "palladium:ability_unlocked",
                "ability": "armor"
              }
            ]
          }
        ]
      }
    },
    "armor_activate.command": {
      "type": "satsu_iron_man_addon:scoreboard_ability",
      "hidden": true,
      "hidden_in_bar": true,
      "score": "satsu.iron.man.armor.actived",
      "adjustment_type": "set",
      "adjustment_amount": 1,
      "conditions": {
        "enabling": [
          {
            "type": "palladium:objective_score",
            "objective": "satsu.iron.man.animation.armor",
            "min_score": 1,
            "max_score": 1
          },
          {
            "type": "palladium:ability_integer_property",
            "ability": "armor_activate.animation_timer.every",
            "property": "value",
            "min": 10,
            "max": 19
          }
        ],
        "unlocking": []
      }
    },
    "armor_activate.animation_timer.command": {
      "type": "palladium:dummy",
      "icon": "#satsu_iron_man_addon:enable_armor_icon",
      "title": { "translate": "ability.title.satsu.enable_armor" },
      "hidden": true,
      "hidden_in_bar": false,
      "list_index": 1,
      "conditions": {
        "enabling": [
          {
            "type": "palladium:action",
            "cooldown": 0,
            "key_type": "key_bind",
            "needs_empty_hand": false,
            "allow_scrolling_when_crouching": true
          }
        ],
        "unlocking": [
          {
            "type": "palladium:ability_enabled",
            "ability": "dummy"
          },
          {
            "type": "palladium:integer_property",
            "property": "satsu_iron_man_armor_arc_energy",
            "min": 1,
            "max": 2147483647
          },
          {
            "type": "palladium:command_result",
            "command": "execute as @s if block ~ ~-1 ~ satsu_iron_man_addon:gantry_station"
          },
          {
            "type": "palladium:not",
            "conditions": [
              {
                "type": "palladium:objective_score",
                "objective": "satsu.iron.man.armor.remote",
                "min_score": 1,
                "max_score": 1
              }
            ]
          }
        ]
      }
    },
    "satsu.iron.man.animation.armor.1": {
      "type": "satsu_iron_man_addon:scoreboard_ability",
      "hidden": true,
      "hidden_in_bar": true,
      "score": "satsu.iron.man.animation.armor",
      "adjustment_type": "add",
      "adjustment_amount": 1,
      "conditions": {
        "enabling": [
          {
            "type": "palladium:ability_enabled",
            "ability": "armor_activate.animation_timer.command"
          }
        ],
        "unlocking": []
      }
    },
    "satsu.iron.man.animation.armor.0": {
      "type": "satsu_iron_man_addon:scoreboard_ability",
      "hidden": true,
      "hidden_in_bar": false,
      "score": "satsu.iron.man.animation.armor",
      "adjustment_type": "set",
      "adjustment_amount": 0,
      "conditions": {
        "enabling": [
          {
            "type": "palladium:objective_score",
            "objective": "satsu.iron.man.animation.armor",
            "min_score": 2
          }
        ],
        "unlocking": []
      }
    }
  }
}
