{
	"format_version": "1.12.0",
	"minecraft:geometry": [
		{
			"description": {
				"identifier": "geometry.unknown",
				"texture_width": 64,
				"texture_height": 64,
				"visible_bounds_width": 5,
				"visible_bounds_height": 4.5,
				"visible_bounds_offset": [0, 1.75, 0]
			},
			"bones": [
				{
					"name": "armorHead",
					"pivot": [6.00064, 24.83479, -0.825]
				},
				{
					"name": "drone",
					"parent": "armorHead",
					"pivot": [24.20064, 28.33479, -0.825],
					"cubes": [
						{
							"origin": [17.35064, 26.38479, -3.825],
							"size": [5.3, 3.9, 6],
							"inflate": 0.5,
							"uv": {
								"north": {"uv": [20, 36], "uv_size": [8, 6]},
								"east": {"uv": [11, 36], "uv_size": [9, 6]},
								"south": {"uv": [37, 36], "uv_size": [8, 6]},
								"west": {"uv": [28, 36], "uv_size": [9, 6]},
								"up": {"uv": [20, 27], "uv_size": [8, 9]},
								"down": {"uv": [28, 36], "uv_size": [8, -9]}
							}
						},
						{
							"origin": [14.90064, 27.08479, -3.125],
							"size": [1.8, 2.5, 4.6],
							"inflate": 0.5,
							"pivot": [16.15064, 28.33479, -0.825],
							"rotation": [0, 0, 7.5],
							"uv": {
								"north": {"uv": [51, 36], "uv_size": [3, 4]},
								"east": {"uv": [44, 36], "uv_size": [7, 4]},
								"south": {"uv": [61, 36], "uv_size": [3, 4]},
								"west": {"uv": [54, 36], "uv_size": [7, 4]},
								"up": {"uv": [51, 29], "uv_size": [3, 7]},
								"down": {"uv": [54, 36], "uv_size": [3, -7]}
							}
						},
						{
							"origin": [17.35064, 24.98479, -5.225],
							"size": [0.4, 0.4, 4.6],
							"inflate": 0.5,
							"uv": {
								"north": {"uv": [53, 47], "uv_size": [1, 1]},
								"east": {"uv": [46, 47], "uv_size": [7, 1]},
								"south": {"uv": [61, 47], "uv_size": [1, 1]},
								"west": {"uv": [54, 47], "uv_size": [7, 1]},
								"up": {"uv": [53, 40], "uv_size": [1, 7]},
								"down": {"uv": [54, 47], "uv_size": [1, -7]}
							}
						},
						{
							"origin": [16.30064, 25.19479, -5.225],
							"size": [0.05, 0.05, 1.1],
							"inflate": 0.5,
							"uv": {
								"north": {"uv": [53, 47], "uv_size": [2, 1]},
								"east": {"uv": [53, 47], "uv_size": [2, 1]},
								"south": {"uv": [53, 47], "uv_size": [2, 1]},
								"west": {"uv": [53, 47], "uv_size": [2, 1]},
								"up": {"uv": [55, 47], "uv_size": [-1, -2]},
								"down": {"uv": [55, 47], "uv_size": [-1, -2]}
							}
						},
						{
							"origin": [22.25064, 24.98479, -5.225],
							"size": [0.4, 0.4, 4.6],
							"inflate": 0.5,
							"uv": {
								"north": {"uv": [53, 47], "uv_size": [1, 1]},
								"east": {"uv": [46, 47], "uv_size": [7, 1]},
								"south": {"uv": [61, 47], "uv_size": [1, 1]},
								"west": {"uv": [54, 47], "uv_size": [7, 1]},
								"up": {"uv": [53, 40], "uv_size": [1, 7]},
								"down": {"uv": [54, 47], "uv_size": [1, -7]}
							}
						},
						{
							"origin": [23.30064, 27.08479, -3.125],
							"size": [1.8, 2.5, 4.6],
							"inflate": 0.5,
							"pivot": [24.20064, 28.33479, -0.825],
							"rotation": [0, 0, -7.5],
							"uv": {
								"north": {"uv": [54, 36], "uv_size": [-3, 4]},
								"east": {"uv": [61, 36], "uv_size": [-7, 4]},
								"south": {"uv": [64, 36], "uv_size": [-3, 4]},
								"west": {"uv": [51, 36], "uv_size": [-7, 4]},
								"up": {"uv": [54, 29], "uv_size": [-3, 7]},
								"down": {"uv": [57, 36], "uv_size": [-3, -7]}
							}
						},
						{
							"origin": [23.65064, 25.19479, -5.225],
							"size": [0.05, 0.05, 1.1],
							"inflate": 0.5,
							"uv": {
								"north": {"uv": [53, 47], "uv_size": [2, 1]},
								"east": {"uv": [53, 47], "uv_size": [2, 1]},
								"south": {"uv": [53, 47], "uv_size": [2, 1]},
								"west": {"uv": [53, 47], "uv_size": [2, 1]},
								"up": {"uv": [55, 47], "uv_size": [-1, -2]},
								"down": {"uv": [55, 47], "uv_size": [-1, -2]}
							}
						},
						{
							"origin": [-22.65064, 26.38479, -3.825],
							"size": [5.3, 3.9, 6],
							"inflate": 0.5,
							"uv": {
								"north": {"uv": [28, 36], "uv_size": [-8, 6]},
								"east": {"uv": [37, 36], "uv_size": [-9, 6]},
								"south": {"uv": [45, 36], "uv_size": [-8, 6]},
								"west": {"uv": [20, 36], "uv_size": [-9, 6]},
								"up": {"uv": [28, 27], "uv_size": [-8, 9]},
								"down": {"uv": [36, 36], "uv_size": [-8, -9]}
							}
						},
						{
							"origin": [-16.70064, 27.08479, -3.125],
							"size": [1.8, 2.5, 4.6],
							"inflate": 0.5,
							"pivot": [-16.15064, 28.33479, -0.825],
							"rotation": [0, 0, -7.5],
							"uv": {
								"north": {"uv": [54, 36], "uv_size": [-3, 4]},
								"east": {"uv": [61, 36], "uv_size": [-7, 4]},
								"south": {"uv": [64, 36], "uv_size": [-3, 4]},
								"west": {"uv": [51, 36], "uv_size": [-7, 4]},
								"up": {"uv": [54, 29], "uv_size": [-3, 7]},
								"down": {"uv": [57, 36], "uv_size": [-3, -7]}
							}
						},
						{
							"origin": [-17.75064, 24.98479, -5.225],
							"size": [0.4, 0.4, 4.6],
							"inflate": 0.5,
							"uv": {
								"north": {"uv": [54, 47], "uv_size": [-1, 1]},
								"east": {"uv": [61, 47], "uv_size": [-7, 1]},
								"south": {"uv": [62, 47], "uv_size": [-1, 1]},
								"west": {"uv": [53, 47], "uv_size": [-7, 1]},
								"up": {"uv": [54, 40], "uv_size": [-1, 7]},
								"down": {"uv": [55, 47], "uv_size": [-1, -7]}
							}
						},
						{
							"origin": [-16.35064, 25.19479, -5.225],
							"size": [0.05, 0.05, 1.1],
							"inflate": 0.5,
							"uv": {
								"north": {"uv": [55, 47], "uv_size": [-2, 1]},
								"east": {"uv": [55, 47], "uv_size": [-2, 1]},
								"south": {"uv": [55, 47], "uv_size": [-2, 1]},
								"west": {"uv": [55, 47], "uv_size": [-2, 1]},
								"up": {"uv": [54, 47], "uv_size": [1, -2]},
								"down": {"uv": [54, 47], "uv_size": [1, -2]}
							}
						},
						{
							"origin": [-22.65064, 24.98479, -5.225],
							"size": [0.4, 0.4, 4.6],
							"inflate": 0.5,
							"uv": {
								"north": {"uv": [54, 47], "uv_size": [-1, 1]},
								"east": {"uv": [61, 47], "uv_size": [-7, 1]},
								"south": {"uv": [62, 47], "uv_size": [-1, 1]},
								"west": {"uv": [53, 47], "uv_size": [-7, 1]},
								"up": {"uv": [54, 40], "uv_size": [-1, 7]},
								"down": {"uv": [55, 47], "uv_size": [-1, -7]}
							}
						},
						{
							"origin": [-25.10064, 27.08479, -3.125],
							"size": [1.8, 2.5, 4.6],
							"inflate": 0.5,
							"pivot": [-24.20064, 28.33479, -0.825],
							"rotation": [0, 0, 7.5],
							"uv": {
								"north": {"uv": [51, 36], "uv_size": [3, 4]},
								"east": {"uv": [44, 36], "uv_size": [7, 4]},
								"south": {"uv": [61, 36], "uv_size": [3, 4]},
								"west": {"uv": [54, 36], "uv_size": [7, 4]},
								"up": {"uv": [51, 29], "uv_size": [3, 7]},
								"down": {"uv": [54, 36], "uv_size": [3, -7]}
							}
						},
						{
							"origin": [-23.70064, 25.19479, -5.225],
							"size": [0.05, 0.05, 1.1],
							"inflate": 0.5,
							"uv": {
								"north": {"uv": [55, 47], "uv_size": [-2, 1]},
								"east": {"uv": [55, 47], "uv_size": [-2, 1]},
								"south": {"uv": [55, 47], "uv_size": [-2, 1]},
								"west": {"uv": [55, 47], "uv_size": [-2, 1]},
								"up": {"uv": [54, 47], "uv_size": [1, -2]},
								"down": {"uv": [54, 47], "uv_size": [1, -2]}
							}
						}
					]
				},
				{
					"name": "armorBody",
					"pivot": [6.00064, 24.83479, -0.825]
				},
				{
					"name": "bone2",
					"parent": "armorBody",
					"pivot": [2.85064, 24.83479, 3.025]
				},
				{
					"name": "bone",
					"parent": "armorBody",
					"pivot": [9.15064, 24.83479, 3.025]
				},
				{
					"name": "bone3",
					"parent": "armorBody",
					"pivot": [2.85064, 16.43479, 3.025]
				},
				{
					"name": "bone4",
					"parent": "armorBody",
					"pivot": [9.15064, 16.43479, 3.025]
				},
				{
					"name": "armorRightArm",
					"pivot": [2.50064, 23.43479, -0.825]
				},
				{
					"name": "armorLeftArm",
					"pivot": [9.50064, 23.43479, -0.825]
				},
				{
					"name": "armorRightLeg",
					"pivot": [4.67064, 16.43479, -0.825]
				},
				{
					"name": "armorLeftLeg",
					"pivot": [7.33064, 16.43479, -0.825]
				}
			]
		}
	]
}