{
  "type": "palladium:compound",
  "layers": [
    {
      "type": "geckolib:default",
      "model": "satsu_iron_man_addon:geo/armor_models/iron_man/full_body/main.geo.json",
      "texture": {
        "base": "satsu_iron_man_addon:textures/models/iron_man/no_light/iron_man_suit_#X_1.png",
        "transformers": [
          {
            "type": "palladium:alpha_mask",
            "mask": "satsu_iron_man_addon:textures/models/alpha_masks/stealh_modes/transformation_#STEALH.png"
          }
        ],
        "variables": {
          "STEALH": {
            "type": "palladium:ability_integer_property",
            "power": "satsu_iron_man_addon:armor_set/armors",
            "ability": "stealht_animation_timer",
            "property": "value",
            "min": 0,
            "max": 17
          },
          "X": {
            "type": "palladium:objective_score",
            "objective": "satsu.iron.man.armor",
            "min": 1
          },
          "Y": {
            "type": "palladium:integer_property",
            "property": "satsu_mask_value",
            "min": 0
          }
        },
        "output": "satsu_iron_man_addon:textures/models/armor/iron_man_suit_#X_1_#STEALH"
      },
      "conditions": [
        {
          "type": "palladium:or",
          "conditions": [
            {
              "type": "palladium:objective_score",
              "objective": "satsu.iron.man.armor",
              "min_score": 16,
              "max_score": 16
            },
            {
              "type": "palladium:objective_score",
              "objective": "satsu.iron.man.armor",
              "min_score": 9,
              "max_score": 9
            },
            {
              "type": "palladium:objective_score",
              "objective": "satsu.iron.man.armor",
              "min_score": 11,
              "max_score": 11
            },
            {
              "type": "palladium:objective_score",
              "objective": "satsu.iron.man.armor",
              "min_score": 15,
              "max_score": 15
            },
            {
              "type": "palladium:objective_score",
              "objective": "satsu.iron.man.armor",
              "min_score": 18,
              "max_score": 18
            },
            {
              "type": "palladium:objective_score",
              "objective": "satsu.iron.man.armor",
              "min_score": 23,
              "max_score": 23
            },
            {
              "type": "palladium:objective_score",
              "objective": "satsu.iron.man.armor",
              "min_score": 27,
              "max_score": 27
            }
          ]
        }
      ]
    },
    {
      "type": "geckolib:default",
      "model": "satsu_iron_man_addon:geo/armor_models/iron_man/full_body/main.geo.json",
      "texture": {
        "base": "satsu_iron_man_addon:textures/models/iron_man/light/iron_man_suit_lights_#X_1.png",
        "transformers": [
          {
            "type": "palladium:alpha_mask",
            "mask": "satsu_iron_man_addon:textures/models/alpha_masks/stealh_modes/transformation_#STEALH.png"
          }
        ],
        "variables": {
          "STEALH": {
            "type": "palladium:ability_integer_property",
            "power": "satsu_iron_man_addon:armor_set/armors",
            "ability": "stealht_animation_timer",
            "property": "value",
            "min": 0,
            "max": 17
          },
          "X": {
            "type": "palladium:objective_score",
            "objective": "satsu.iron.man.armor",
            "min": 1
          }
        },
        "output": "satsu_iron_man_addon:textures/models/armor/iron_man_suit_lights_#X_1_#STEALH"
      },
      "conditions": [
        {
          "type": "palladium:or",
          "conditions": [
            {
              "type": "palladium:objective_score",
              "objective": "satsu.iron.man.armor",
              "min_score": 16,
              "max_score": 16
            },
            {
              "type": "palladium:objective_score",
              "objective": "satsu.iron.man.armor",
              "min_score": 9,
              "max_score": 9
            },
            {
              "type": "palladium:objective_score",
              "objective": "satsu.iron.man.armor",
              "min_score": 11,
              "max_score": 11
            },
            {
              "type": "palladium:objective_score",
              "objective": "satsu.iron.man.armor",
              "min_score": 15,
              "max_score": 15
            },
            {
              "type": "palladium:objective_score",
              "objective": "satsu.iron.man.armor",
              "min_score": 18,
              "max_score": 18
            },
            {
              "type": "palladium:objective_score",
              "objective": "satsu.iron.man.armor",
              "min_score": 23,
              "max_score": 23
            },
            {
              "type": "palladium:objective_score",
              "objective": "satsu.iron.man.armor",
              "min_score": 27,
              "max_score": 27
            }
          ]
        },
        {
          "type": "palladium:or",
          "conditions": [
            {
              "type": "palladium:integer_property",
              "property": "satsu_iron_man_armor_arc_energy",
              "min": 1,
              "max": 2147483647
            }
          ]
        }
      ]
    },
    {
      "type": "geckolib:default",
      "model": "satsu_iron_man_addon:geo/armor_models/iron_man/full_body/main.geo.json",
      "texture": {
        "base": "satsu_iron_man_addon:textures/models/iron_man/no_light/iron_man_suit_#X_2.png",
        "transformers": [
          {
            "type": "palladium:alpha_mask",
            "mask": "satsu_iron_man_addon:textures/models/alpha_masks/stealh_modes/transformation_#STEALH_night.png"
          }
        ],
        "variables": {
          "STEALH_night": {
            "type": "palladium:ability_integer_property",
            "power": "satsu_iron_man_addon:armor_set/armors",
            "ability": "stealht_night_animation_timer",
            "property": "value",
            "min": 0,
            "max": 17
          },
          "X": {
            "type": "palladium:objective_score",
            "objective": "satsu.iron.man.armor",
            "min_score": 6,
            "max_score": 33
          },
          "Y": {
            "type": "palladium:integer_property",
            "property": "satsu_mask_value",
            "min": 0
          }
        },
        "output": "satsu_iron_man_addon:textures/models/armor/stealht_night/iron_man_suit_#X_2_#STEALH_night"
      },
      "conditions": [
        {
          "type": "palladium:or",
          "conditions": [
            {
              "type": "palladium:integer_property",
              "property": "satsu_iron_man_armor_arc_energy",
              "min": 1,
              "max": 2147483647
            }
          ]
        },
        {
          "type": "palladium:or",
          "conditions": [
            {
              "type": "palladium:objective_score",
              "objective": "satsu.iron.man.armor",
              "min_score": 16,
              "max_score": 16
            },
            {
              "type": "palladium:objective_score",
              "objective": "satsu.iron.man.armor",
              "min_score": 18,
              "max_score": 18
            }
          ]
        },
        {
          "type": "palladium:ability_integer_property",
          "power": "satsu_iron_man_addon:armor_principal/iron_man_armor",
          "ability": "no_nanoarmor_anim",
          "property": "value",
          "min": 1,
          "max": 16
        }
      ]
    },
    {
      "type": "geckolib:default",
      "model": "satsu_iron_man_addon:geo/armor_models/iron_man/full_body/main.geo.json",
      "texture": {
        "base": "satsu_iron_man_addon:textures/models/iron_man/light/iron_man_suit_lights_#X_2.png",
        "transformers": [
          {
            "type": "palladium:alpha_mask",
            "mask": "satsu_iron_man_addon:textures/models/alpha_masks/stealh_modes/transformation_#STEALH_night.png"
          }
        ],
        "variables": {
          "STEALH_night": {
            "type": "palladium:ability_integer_property",
            "power": "satsu_iron_man_addon:armor_set/armors",
            "ability": "stealht_night_animation_timer",
            "property": "value",
            "min": 0,
            "max": 17
          },
          "X": {
            "type": "palladium:objective_score",
            "objective": "satsu.iron.man.armor",
            "min_score": 6,
            "max_score": 33
          }
        },
        "output": "satsu_iron_man_addon:textures/models/armor/stealht_night/iron_man_suit_lights_#X_2_#STEALH_night"
      },
      "conditions": [
        {
          "type": "palladium:or",
          "conditions": [
            {
              "type": "palladium:objective_score",
              "objective": "satsu.iron.man.armor",
              "min_score": 16,
              "max_score": 16
            },
            {
              "type": "palladium:objective_score",
              "objective": "satsu.iron.man.armor",
              "min_score": 18,
              "max_score": 18
            }
          ]
        },
        {
          "type": "palladium:or",
          "conditions": [
            {
              "type": "palladium:integer_property",
              "property": "satsu_iron_man_armor_arc_energy",
              "min": 1,
              "max": 2147483647
            }
          ]
        },
        {
          "type": "palladium:ability_integer_property",
          "power": "satsu_iron_man_addon:armor_principal/iron_man_armor",
          "ability": "no_nanoarmor_anim",
          "property": "value",
          "min": 1,
          "max": 16
        }
      ]
    },
    {
      "type": "geckolib:default",
      "model": "satsu_iron_man_addon:geo/armor_models/iron_man/full_body/main.geo.json",
      "texture": {
        "base": "satsu_iron_man_addon:textures/models/iron_man/no_light/iron_man_suit_#X_3.png",
        "transformers": [
          {
            "type": "palladium:alpha_mask",
            "mask": "satsu_iron_man_addon:textures/models/alpha_masks/stealh_modes/transformation_#STEALH.png"
          }
        ],
        "variables": {
          "STEALH": {
            "type": "palladium:ability_integer_property",
            "power": "satsu_iron_man_addon:armor_set/armors",
            "ability": "stealht_animation_timer",
            "property": "value",
            "min": 0,
            "max": 17
          },
          "X": {
            "type": "palladium:objective_score",
            "objective": "satsu.iron.man.armor",
            "min_score": 6,
            "max_score": 33
          },
          "Y": {
            "type": "palladium:integer_property",
            "property": "satsu_mask_value",
            "min": 0
          }
        },
        "output": "satsu_iron_man_addon:textures/models/armor/iron_man_suit_#X_3_#STEALH"
      },
      "conditions": [
        {
          "type": "palladium:or",
          "conditions": [
            {
              "type": "palladium:objective_score",
              "objective": "satsu.iron.man.armor",
              "min_score": 16,
              "max_score": 16
            },
            {
              "type": "palladium:objective_score",
              "objective": "satsu.iron.man.armor",
              "min_score": 18,
              "max_score": 18
            }
          ]
        },
        {
          "type": "palladium:ability_integer_property",
          "power": "satsu_iron_man_addon:armor_set/armors",
          "ability": "stealht_night_animation_timer",
          "property": "value",
          "min": 16,
          "max": 17
        }
      ]
    },
    {
      "type": "geckolib:default",
      "model": "satsu_iron_man_addon:geo/armor_models/iron_man/full_body/main.geo.json",
      "texture": {
        "base": "satsu_iron_man_addon:textures/models/iron_man/light/iron_man_suit_lights_#X_3.png",
        "transformers": [
          {
            "type": "palladium:alpha_mask",
            "mask": "satsu_iron_man_addon:textures/models/alpha_masks/stealh_modes/transformation_#STEALH.png"
          }
        ],
        "variables": {
          "STEALH": {
            "type": "palladium:ability_integer_property",
            "power": "satsu_iron_man_addon:armor_set/armors",
            "ability": "stealht_animation_timer",
            "property": "value",
            "min": 0,
            "max": 17
          },
          "X": {
            "type": "palladium:objective_score",
            "objective": "satsu.iron.man.armor",
            "min_score": 6,
            "max_score": 33
          }
        },
        "output": "satsu_iron_man_addon:textures/models/armor/iron_man_suit_lights_#X_3_#STEALH"
      },
      "conditions": [
        {
          "type": "palladium:or",
          "conditions": [
            {
              "type": "palladium:objective_score",
              "objective": "satsu.iron.man.armor",
              "min_score": 16,
              "max_score": 16
            },
            {
              "type": "palladium:objective_score",
              "objective": "satsu.iron.man.armor",
              "min_score": 18,
              "max_score": 18
            }
          ]
        },
        {
          "type": "palladium:or",
          "conditions": [
            {
              "type": "palladium:integer_property",
              "property": "satsu_iron_man_armor_arc_energy",
              "min": 1,
              "max": 2147483647
            }
          ]
        },
        {
          "type": "palladium:ability_integer_property",
          "power": "satsu_iron_man_addon:armor_set/armors",
          "ability": "stealht_night_animation_timer",
          "property": "value",
          "min": 16,
          "max": 17
        }
      ]
    }
  ]
}
